{
  "schema_id": "https://wrkr.dev/schemas/v1/proposed-action-contract-artifact.schema.json",
  "schema_version": "1",
  "artifact_id": "paca-c096858fefbcf3fd",
  "contract_id": "pac-5e608596dec5cbb2",
  "contract_family_id": "pacf-6dd3f601d0fa58eb",
  "revision": 1,
  "producer": {
    "name": "wrkr",
    "artifact_schema_version": "1",
    "contract_schema_version": "3"
  },
  "source_scan_refs": [
    "saved_scan:v1"
  ],
  "composition_refs": [
    "cap-0653e7cbe88f7adf"
  ],
  "resolution_key": "rk-198c61f65a932a9e+rk-95c14e9fdd46075b",
  "creation_evidence": [
    "wch-2514b320edea",
    "wch-63302c190caa"
  ],
  "canonical_content_digest": "sha256:c096858fefbcf3fde76c1add57f83b73fa0c4461066eeeeaaa7bd640143ba662",
  "variant": {
    "share_profile": "internal",
    "redacted": false
  },
  "report_only": true,
  "contract": {
    "contract_id": "pac-5e608596dec5cbb2",
    "contract_family_id": "pacf-6dd3f601d0fa58eb",
    "contract_content_digest": "sha256:70a7d9d61fe19a7d01382df7fc44a40729cbc7c3991e8824cf60b8a718d68f8c",
    "contract_version": "3",
    "contract_kind": "proposed_action_contract",
    "composition_ref": "cap-0653e7cbe88f7adf",
    "resolution_key": "rk-198c61f65a932a9e+rk-95c14e9fdd46075b",
    "prohibited_transitions": [
      {
        "transition_id": "cat-bd84ada007470660",
        "from_stage_id": "cas-9b871b9cb6fbbe5b",
        "to_stage_id": "cas-653ad7b5691b8c61",
        "from_role": "source",
        "to_role": "privileged_sink",
        "reason": "composition_transition"
      }
    ],
    "target_constraints": [
      {
        "key": "composition_id",
        "value": "cap-0653e7cbe88f7adf"
      },
      {
        "key": "environment",
        "value": "production"
      },
      {
        "key": "outcome_class",
        "value": "release_publish"
      },
      {
        "key": "target_class",
        "value": "production_impacting"
      },
      {
        "key": "target_identity",
        "value": "built_in:deploy_workflow+built_in:kubernetes+built_in:release_automation"
      }
    ],
    "required_credential_mode": "ephemeral",
    "maximum_delegation_depth": 1,
    "evidence_requirements": [
      "action_outcome",
      "approval",
      "credential_attenuation",
      "delegation_relationship",
      "jit_credential",
      "policy_decision",
      "proof_verification",
      "runtime_token_propagation"
    ],
    "acceptable_countersigners": [
      "control_owner",
      "security_reviewer"
    ],
    "expected_outcome_class": "release_publish",
    "compensation_required": true,
    "source_digests": [
      "sha256:230a8a1e7604fcfe42abf74085d6c055d360082a0fc92da46f6c252d88fbfbf7"
    ],
    "report_only": true,
    "readiness_state": "needs_evidence",
    "reason_codes": [
      "authority:unresolved:affected_system_owner",
      "authority:unresolved:business_owner",
      "authority:unresolved:credential_subject_constraint",
      "authority:unresolved:delegation_root",
      "authority:unresolved:originating_intent",
      "authority:unresolved:permitted_agent_role",
      "authority:unresolved:policy_authority",
      "authority:unresolved:requester_identity",
      "authority:unresolved:separation_of_duties",
      "compensation:unresolved",
      "composition:delegation_broadened",
      "composition:evidence_incomplete",
      "expiry:deterministic_source_absent",
      "precondition:unresolved:credential_mode",
      "precondition:unresolved:effect_contract",
      "precondition:unresolved:environment",
      "precondition:unresolved:expected_effect",
      "precondition:unresolved:forbidden_effect",
      "precondition:unresolved:freshness",
      "precondition:unresolved:policy_digest",
      "precondition:unresolved:producer",
      "precondition:unresolved:required_check",
      "precondition:unresolved:sandbox",
      "precondition:unresolved:target",
      "precondition:unresolved:validation_contract",
      "readiness:needs_delegation_attenuation_evidence",
      "readiness:needs_proof_evidence",
      "recommended_control:block_standing_credential",
      "report_only:true"
    ],
    "revision": 1,
    "authority_requirements": [
      {
        "requirement_id": "pacr-08178f15ef8e2b27",
        "kind": "policy_authority",
        "required_constraint": "policy_authority:required",
        "evidence_state": "unknown",
        "freshness_state": "unknown",
        "evidence_refs": [
          ".gait/policy.yaml",
          "approval_status=unapproved",
          "baseline:discovered_surface",
          "credential_likely_scope:source_control_write",
          "credential_present:true",
          "credential_referenced_by_workflow:true",
          "credential_target_system:source_control",
          "matched_target:built_in:deploy_workflow",
          "matched_target:built_in:kubernetes",
          "matched_target:built_in:release_automation",
          "permission:deploy.write",
          "permission:deployments.write",
          "permission:pull_request.write",
          "permission:repo.write",
          "repo_workflow_secret_correlation",
          "scope:source_control_write",
          "subject:cloud_admin_key",
          "target_system:source_control",
          "wch-2514b320edea",
          "wch-63302c190caa",
          "workflow_secret_refs",
          "write_path:deploy",
          "write_path:write_capable",
          "write_path_class:deploy_write",
          "write_path_class:pr_write",
          "write_path_class:production_adjacent_write",
          "write_path_class:release_write",
          "write_path_class:repo_write",
          "write_path_class:write"
        ],
        "reason_codes": [
          "authority:policy_authority:missing",
          "authority:policy_authority:unknown"
        ]
      },
      {
        "requirement_id": "pacr-4a509e0cb3141753",
        "kind": "delegation_root",
        "required_constraint": "delegation_root:required",
        "observed_value": "authority-b3aed31f4204875e",
        "evidence_state": "unknown",
        "freshness_state": "unknown",
        "evidence_refs": [
          ".gait/policy.yaml",
          "approval_status=unapproved",
          "baseline:discovered_surface",
          "credential_likely_scope:source_control_write",
          "credential_present:true",
          "credential_referenced_by_workflow:true",
          "credential_target_system:source_control",
          "matched_target:built_in:deploy_workflow",
          "matched_target:built_in:kubernetes",
          "matched_target:built_in:release_automation",
          "permission:deploy.write",
          "permission:deployments.write",
          "permission:pull_request.write",
          "permission:repo.write",
          "repo_workflow_secret_correlation",
          "scope:source_control_write",
          "subject:cloud_admin_key",
          "target_system:source_control",
          "wch-2514b320edea",
          "wch-63302c190caa",
          "workflow_secret_refs",
          "write_path:deploy",
          "write_path:write_capable",
          "write_path_class:deploy_write",
          "write_path_class:pr_write",
          "write_path_class:production_adjacent_write",
          "write_path_class:release_write",
          "write_path_class:repo_write",
          "write_path_class:write"
        ],
        "reason_codes": [
          "authority:delegation_root:unknown"
        ]
      },
      {
        "requirement_id": "pacr-6758294791831216",
        "kind": "separation_of_duties",
        "required_constraint": "requester_must_not_approve",
        "evidence_state": "unknown",
        "freshness_state": "unknown",
        "evidence_refs": [
          ".gait/policy.yaml",
          "approval_status=unapproved",
          "baseline:discovered_surface",
          "credential_likely_scope:source_control_write",
          "credential_present:true",
          "credential_referenced_by_workflow:true",
          "credential_target_system:source_control",
          "matched_target:built_in:deploy_workflow",
          "matched_target:built_in:kubernetes",
          "matched_target:built_in:release_automation",
          "permission:deploy.write",
          "permission:deployments.write",
          "permission:pull_request.write",
          "permission:repo.write",
          "repo_workflow_secret_correlation",
          "scope:source_control_write",
          "subject:cloud_admin_key",
          "target_system:source_control",
          "wch-2514b320edea",
          "wch-63302c190caa",
          "workflow_secret_refs",
          "write_path:deploy",
          "write_path:write_capable",
          "write_path_class:deploy_write",
          "write_path_class:pr_write",
          "write_path_class:production_adjacent_write",
          "write_path_class:release_write",
          "write_path_class:repo_write",
          "write_path_class:write"
        ],
        "reason_codes": [
          "authority:separation_of_duties:missing",
          "authority:separation_of_duties:unknown"
        ]
      },
      {
        "requirement_id": "pacr-781435f42536915c",
        "kind": "requester_identity",
        "required_constraint": "requester_identity:required",
        "observed_value": "stage:cas-9b871b9cb6fbbe5b",
        "evidence_state": "unknown",
        "freshness_state": "unknown",
        "evidence_refs": [
          ".gait/policy.yaml",
          "approval_status=unapproved",
          "baseline:discovered_surface",
          "credential_likely_scope:source_control_write",
          "credential_present:true",
          "credential_referenced_by_workflow:true",
          "credential_target_system:source_control",
          "matched_target:built_in:deploy_workflow",
          "matched_target:built_in:kubernetes",
          "matched_target:built_in:release_automation",
          "permission:deploy.write",
          "permission:deployments.write",
          "permission:pull_request.write",
          "permission:repo.write",
          "repo_workflow_secret_correlation",
          "scope:source_control_write",
          "subject:cloud_admin_key",
          "target_system:source_control",
          "wch-2514b320edea",
          "wch-63302c190caa",
          "workflow_secret_refs",
          "write_path:deploy",
          "write_path:write_capable",
          "write_path_class:deploy_write",
          "write_path_class:pr_write",
          "write_path_class:production_adjacent_write",
          "write_path_class:release_write",
          "write_path_class:repo_write",
          "write_path_class:write"
        ],
        "reason_codes": [
          "authority:requester_identity:unknown"
        ]
      },
      {
        "requirement_id": "pacr-9bd3c82cceec6ae5",
        "kind": "originating_intent",
        "required_constraint": "composition:cap-0653e7cbe88f7adf",
        "observed_value": "package_change_to_release",
        "evidence_state": "unknown",
        "freshness_state": "unknown",
        "evidence_refs": [
          ".gait/policy.yaml",
          "approval_status=unapproved",
          "baseline:discovered_surface",
          "credential_likely_scope:source_control_write",
          "credential_present:true",
          "credential_referenced_by_workflow:true",
          "credential_target_system:source_control",
          "matched_target:built_in:deploy_workflow",
          "matched_target:built_in:kubernetes",
          "matched_target:built_in:release_automation",
          "permission:deploy.write",
          "permission:deployments.write",
          "permission:pull_request.write",
          "permission:repo.write",
          "repo_workflow_secret_correlation",
          "scope:source_control_write",
          "subject:cloud_admin_key",
          "target_system:source_control",
          "wch-2514b320edea",
          "wch-63302c190caa",
          "workflow_secret_refs",
          "write_path:deploy",
          "write_path:write_capable",
          "write_path_class:deploy_write",
          "write_path_class:pr_write",
          "write_path_class:production_adjacent_write",
          "write_path_class:release_write",
          "write_path_class:repo_write",
          "write_path_class:write"
        ],
        "reason_codes": [
          "authority:originating_intent:unknown"
        ]
      },
      {
        "requirement_id": "pacr-ba36d3c10ae8b8ec",
        "kind": "credential_subject_constraint",
        "required_constraint": "subject:built_in:deploy_workflow+built_in:kubernetes+built_in:release_automation",
        "observed_value": "built_in:deploy_workflow+built_in:kubernetes+built_in:release_automation",
        "evidence_state": "unknown",
        "freshness_state": "unknown",
        "evidence_refs": [
          ".gait/policy.yaml",
          "approval_status=unapproved",
          "baseline:discovered_surface",
          "credential_likely_scope:source_control_write",
          "credential_present:true",
          "credential_referenced_by_workflow:true",
          "credential_target_system:source_control",
          "matched_target:built_in:deploy_workflow",
          "matched_target:built_in:kubernetes",
          "matched_target:built_in:release_automation",
          "permission:deploy.write",
          "permission:deployments.write",
          "permission:pull_request.write",
          "permission:repo.write",
          "repo_workflow_secret_correlation",
          "scope:source_control_write",
          "subject:cloud_admin_key",
          "target_system:source_control",
          "wch-2514b320edea",
          "wch-63302c190caa",
          "workflow_secret_refs",
          "write_path:deploy",
          "write_path:write_capable",
          "write_path_class:deploy_write",
          "write_path_class:pr_write",
          "write_path_class:production_adjacent_write",
          "write_path_class:release_write",
          "write_path_class:repo_write",
          "write_path_class:write"
        ],
        "reason_codes": [
          "authority:credential_subject_constraint:unknown"
        ]
      },
      {
        "requirement_id": "pacr-e4441db036f339e3",
        "kind": "affected_system_owner",
        "required_constraint": "affected_system_owner:required",
        "evidence_state": "unknown",
        "freshness_state": "unknown",
        "evidence_refs": [
          ".gait/policy.yaml",
          "approval_status=unapproved",
          "baseline:discovered_surface",
          "credential_likely_scope:source_control_write",
          "credential_present:true",
          "credential_referenced_by_workflow:true",
          "credential_target_system:source_control",
          "matched_target:built_in:deploy_workflow",
          "matched_target:built_in:kubernetes",
          "matched_target:built_in:release_automation",
          "permission:deploy.write",
          "permission:deployments.write",
          "permission:pull_request.write",
          "permission:repo.write",
          "repo_workflow_secret_correlation",
          "scope:source_control_write",
          "subject:cloud_admin_key",
          "target_system:source_control",
          "wch-2514b320edea",
          "wch-63302c190caa",
          "workflow_secret_refs",
          "write_path:deploy",
          "write_path:write_capable",
          "write_path_class:deploy_write",
          "write_path_class:pr_write",
          "write_path_class:production_adjacent_write",
          "write_path_class:release_write",
          "write_path_class:repo_write",
          "write_path_class:write"
        ],
        "reason_codes": [
          "authority:affected_system_owner:missing",
          "authority:affected_system_owner:unknown"
        ]
      },
      {
        "requirement_id": "pacr-e4db5a7bf27a6b6b",
        "kind": "permitted_agent_role",
        "required_constraint": "roles:privileged_sink,source",
        "observed_value": "privileged_sink,source",
        "evidence_state": "unknown",
        "freshness_state": "unknown",
        "evidence_refs": [
          ".gait/policy.yaml",
          "approval_status=unapproved",
          "baseline:discovered_surface",
          "credential_likely_scope:source_control_write",
          "credential_present:true",
          "credential_referenced_by_workflow:true",
          "credential_target_system:source_control",
          "matched_target:built_in:deploy_workflow",
          "matched_target:built_in:kubernetes",
          "matched_target:built_in:release_automation",
          "permission:deploy.write",
          "permission:deployments.write",
          "permission:pull_request.write",
          "permission:repo.write",
          "repo_workflow_secret_correlation",
          "scope:source_control_write",
          "subject:cloud_admin_key",
          "target_system:source_control",
          "wch-2514b320edea",
          "wch-63302c190caa",
          "workflow_secret_refs",
          "write_path:deploy",
          "write_path:write_capable",
          "write_path_class:deploy_write",
          "write_path_class:pr_write",
          "write_path_class:production_adjacent_write",
          "write_path_class:release_write",
          "write_path_class:repo_write",
          "write_path_class:write"
        ],
        "reason_codes": [
          "authority:permitted_agent_role:unknown"
        ]
      },
      {
        "requirement_id": "pacr-ecda69edd00e59f3",
        "kind": "business_owner",
        "required_constraint": "business_owner:required",
        "evidence_state": "unknown",
        "freshness_state": "unknown",
        "evidence_refs": [
          ".gait/policy.yaml",
          "approval_status=unapproved",
          "baseline:discovered_surface",
          "credential_likely_scope:source_control_write",
          "credential_present:true",
          "credential_referenced_by_workflow:true",
          "credential_target_system:source_control",
          "matched_target:built_in:deploy_workflow",
          "matched_target:built_in:kubernetes",
          "matched_target:built_in:release_automation",
          "permission:deploy.write",
          "permission:deployments.write",
          "permission:pull_request.write",
          "permission:repo.write",
          "repo_workflow_secret_correlation",
          "scope:source_control_write",
          "subject:cloud_admin_key",
          "target_system:source_control",
          "wch-2514b320edea",
          "wch-63302c190caa",
          "workflow_secret_refs",
          "write_path:deploy",
          "write_path:write_capable",
          "write_path_class:deploy_write",
          "write_path_class:pr_write",
          "write_path_class:production_adjacent_write",
          "write_path_class:release_write",
          "write_path_class:repo_write",
          "write_path_class:write"
        ],
        "reason_codes": [
          "authority:business_owner:missing",
          "authority:business_owner:unknown"
        ]
      }
    ],
    "authority_readiness_state": "needs_evidence",
    "preconditions": [
      {
        "requirement_id": "pacp-087874f93b15d9f2",
        "kind": "environment",
        "required_constraint": "environment:declared",
        "observed_value": "production",
        "observed_result": "production",
        "acceptable_producers": [
          "control_declaration",
          "gait_policy"
        ],
        "max_age": "PT24H",
        "evidence_state": "unknown",
        "freshness_state": "unknown",
        "evidence_refs": [
          ".gait/policy.yaml",
          "approval_status=unapproved",
          "baseline:discovered_surface",
          "credential_likely_scope:source_control_write",
          "credential_present:true",
          "credential_referenced_by_workflow:true",
          "credential_target_system:source_control",
          "matched_target:built_in:deploy_workflow",
          "matched_target:built_in:kubernetes",
          "matched_target:built_in:release_automation",
          "permission:deploy.write",
          "permission:deployments.write",
          "permission:pull_request.write",
          "permission:repo.write",
          "repo_workflow_secret_correlation",
          "scope:source_control_write",
          "subject:cloud_admin_key",
          "target_system:source_control",
          "wch-2514b320edea",
          "wch-63302c190caa",
          "workflow_secret_refs",
          "write_path:deploy",
          "write_path:write_capable",
          "write_path_class:deploy_write",
          "write_path_class:pr_write",
          "write_path_class:production_adjacent_write",
          "write_path_class:release_write",
          "write_path_class:repo_write",
          "write_path_class:write"
        ],
        "reason_codes": [
          "precondition:environment:unknown"
        ]
      },
      {
        "requirement_id": "pacp-426573989e45a6b2",
        "kind": "freshness",
        "required_constraint": "fresh",
        "observed_value": "unknown",
        "observed_result": "unknown",
        "acceptable_producers": [
          "evidence_policy"
        ],
        "max_age": "PT24H",
        "evidence_state": "unknown",
        "freshness_state": "unknown",
        "evidence_refs": [
          ".gait/policy.yaml",
          "approval_status=unapproved",
          "baseline:discovered_surface",
          "credential_likely_scope:source_control_write",
          "credential_present:true",
          "credential_referenced_by_workflow:true",
          "credential_target_system:source_control",
          "matched_target:built_in:deploy_workflow",
          "matched_target:built_in:kubernetes",
          "matched_target:built_in:release_automation",
          "permission:deploy.write",
          "permission:deployments.write",
          "permission:pull_request.write",
          "permission:repo.write",
          "repo_workflow_secret_correlation",
          "scope:source_control_write",
          "subject:cloud_admin_key",
          "target_system:source_control",
          "wch-2514b320edea",
          "wch-63302c190caa",
          "workflow_secret_refs",
          "write_path:deploy",
          "write_path:write_capable",
          "write_path_class:deploy_write",
          "write_path_class:pr_write",
          "write_path_class:production_adjacent_write",
          "write_path_class:release_write",
          "write_path_class:repo_write",
          "write_path_class:write"
        ],
        "reason_codes": [
          "precondition:freshness:not_fresh",
          "precondition:freshness:unknown"
        ]
      },
      {
        "requirement_id": "pacp-4bf9f04ba9d9aef9",
        "kind": "validation_contract",
        "required_constraint": "validation_contract:required",
        "acceptable_producers": [
          "control_declaration",
          "gait_policy"
        ],
        "max_age": "PT24H",
        "evidence_state": "unknown",
        "freshness_state": "unknown",
        "evidence_refs": [
          ".gait/policy.yaml",
          "approval_status=unapproved",
          "baseline:discovered_surface",
          "credential_likely_scope:source_control_write",
          "credential_present:true",
          "credential_referenced_by_workflow:true",
          "credential_target_system:source_control",
          "matched_target:built_in:deploy_workflow",
          "matched_target:built_in:kubernetes",
          "matched_target:built_in:release_automation",
          "permission:deploy.write",
          "permission:deployments.write",
          "permission:pull_request.write",
          "permission:repo.write",
          "repo_workflow_secret_correlation",
          "scope:source_control_write",
          "subject:cloud_admin_key",
          "target_system:source_control",
          "wch-2514b320edea",
          "wch-63302c190caa",
          "workflow_secret_refs",
          "write_path:deploy",
          "write_path:write_capable",
          "write_path_class:deploy_write",
          "write_path_class:pr_write",
          "write_path_class:production_adjacent_write",
          "write_path_class:release_write",
          "write_path_class:repo_write",
          "write_path_class:write"
        ],
        "reason_codes": [
          "precondition:validation_contract:missing",
          "precondition:validation_contract:unknown"
        ]
      },
      {
        "requirement_id": "pacp-713293589be153ab",
        "kind": "policy_digest",
        "required_constraint": "policy_digest:required",
        "observed_value": "sha256:230a8a1e7604fcfe42abf74085d6c055d360082a0fc92da46f6c252d88fbfbf7",
        "observed_result": "sha256:230a8a1e7604fcfe42abf74085d6c055d360082a0fc92da46f6c252d88fbfbf7",
        "acceptable_producers": [
          "control_declaration",
          "gait_policy"
        ],
        "max_age": "PT24H",
        "evidence_state": "unknown",
        "freshness_state": "unknown",
        "evidence_refs": [
          ".gait/policy.yaml",
          "approval_status=unapproved",
          "baseline:discovered_surface",
          "credential_likely_scope:source_control_write",
          "credential_present:true",
          "credential_referenced_by_workflow:true",
          "credential_target_system:source_control",
          "matched_target:built_in:deploy_workflow",
          "matched_target:built_in:kubernetes",
          "matched_target:built_in:release_automation",
          "permission:deploy.write",
          "permission:deployments.write",
          "permission:pull_request.write",
          "permission:repo.write",
          "repo_workflow_secret_correlation",
          "scope:source_control_write",
          "subject:cloud_admin_key",
          "target_system:source_control",
          "wch-2514b320edea",
          "wch-63302c190caa",
          "workflow_secret_refs",
          "write_path:deploy",
          "write_path:write_capable",
          "write_path_class:deploy_write",
          "write_path_class:pr_write",
          "write_path_class:production_adjacent_write",
          "write_path_class:release_write",
          "write_path_class:repo_write",
          "write_path_class:write"
        ],
        "reason_codes": [
          "precondition:policy_digest:unknown"
        ]
      },
      {
        "requirement_id": "pacp-817324f40e240394",
        "kind": "target",
        "required_constraint": "target:bounded",
        "observed_value": "built_in:deploy_workflow+built_in:kubernetes+built_in:release_automation",
        "observed_result": "built_in:deploy_workflow+built_in:kubernetes+built_in:release_automation",
        "acceptable_producers": [
          "action_path"
        ],
        "max_age": "PT24H",
        "evidence_state": "unknown",
        "freshness_state": "unknown",
        "evidence_refs": [
          ".gait/policy.yaml",
          "approval_status=unapproved",
          "baseline:discovered_surface",
          "credential_likely_scope:source_control_write",
          "credential_present:true",
          "credential_referenced_by_workflow:true",
          "credential_target_system:source_control",
          "matched_target:built_in:deploy_workflow",
          "matched_target:built_in:kubernetes",
          "matched_target:built_in:release_automation",
          "permission:deploy.write",
          "permission:deployments.write",
          "permission:pull_request.write",
          "permission:repo.write",
          "repo_workflow_secret_correlation",
          "scope:source_control_write",
          "subject:cloud_admin_key",
          "target_system:source_control",
          "wch-2514b320edea",
          "wch-63302c190caa",
          "workflow_secret_refs",
          "write_path:deploy",
          "write_path:write_capable",
          "write_path_class:deploy_write",
          "write_path_class:pr_write",
          "write_path_class:production_adjacent_write",
          "write_path_class:release_write",
          "write_path_class:repo_write",
          "write_path_class:write"
        ],
        "reason_codes": [
          "precondition:target:unknown"
        ]
      },
      {
        "requirement_id": "pacp-82b6a6ee6ff2505c",
        "kind": "sandbox",
        "required_constraint": "sandbox:required",
        "acceptable_producers": [
          "control_declaration",
          "gait_policy"
        ],
        "max_age": "PT24H",
        "evidence_state": "unknown",
        "freshness_state": "unknown",
        "evidence_refs": [
          ".gait/policy.yaml",
          "approval_status=unapproved",
          "baseline:discovered_surface",
          "credential_likely_scope:source_control_write",
          "credential_present:true",
          "credential_referenced_by_workflow:true",
          "credential_target_system:source_control",
          "matched_target:built_in:deploy_workflow",
          "matched_target:built_in:kubernetes",
          "matched_target:built_in:release_automation",
          "permission:deploy.write",
          "permission:deployments.write",
          "permission:pull_request.write",
          "permission:repo.write",
          "repo_workflow_secret_correlation",
          "scope:source_control_write",
          "subject:cloud_admin_key",
          "target_system:source_control",
          "wch-2514b320edea",
          "wch-63302c190caa",
          "workflow_secret_refs",
          "write_path:deploy",
          "write_path:write_capable",
          "write_path_class:deploy_write",
          "write_path_class:pr_write",
          "write_path_class:production_adjacent_write",
          "write_path_class:release_write",
          "write_path_class:repo_write",
          "write_path_class:write"
        ],
        "reason_codes": [
          "precondition:sandbox:missing",
          "precondition:sandbox:unknown"
        ]
      },
      {
        "requirement_id": "pacp-8b400c811105d884",
        "kind": "producer",
        "required_constraint": "producer:approved",
        "acceptable_producers": [
          "control_declaration",
          "gait_policy"
        ],
        "max_age": "PT24H",
        "evidence_state": "unknown",
        "freshness_state": "unknown",
        "evidence_refs": [
          ".gait/policy.yaml",
          "approval_status=unapproved",
          "baseline:discovered_surface",
          "credential_likely_scope:source_control_write",
          "credential_present:true",
          "credential_referenced_by_workflow:true",
          "credential_target_system:source_control",
          "matched_target:built_in:deploy_workflow",
          "matched_target:built_in:kubernetes",
          "matched_target:built_in:release_automation",
          "permission:deploy.write",
          "permission:deployments.write",
          "permission:pull_request.write",
          "permission:repo.write",
          "repo_workflow_secret_correlation",
          "scope:source_control_write",
          "subject:cloud_admin_key",
          "target_system:source_control",
          "wch-2514b320edea",
          "wch-63302c190caa",
          "workflow_secret_refs",
          "write_path:deploy",
          "write_path:write_capable",
          "write_path_class:deploy_write",
          "write_path_class:pr_write",
          "write_path_class:production_adjacent_write",
          "write_path_class:release_write",
          "write_path_class:repo_write",
          "write_path_class:write"
        ],
        "reason_codes": [
          "precondition:producer:missing",
          "precondition:producer:unknown"
        ]
      },
      {
        "requirement_id": "pacp-a088f5c197cd550f",
        "kind": "effect_contract",
        "required_constraint": "effect_contract:required",
        "acceptable_producers": [
          "control_declaration",
          "gait_policy"
        ],
        "max_age": "PT24H",
        "evidence_state": "unknown",
        "freshness_state": "unknown",
        "evidence_refs": [
          ".gait/policy.yaml",
          "approval_status=unapproved",
          "baseline:discovered_surface",
          "credential_likely_scope:source_control_write",
          "credential_present:true",
          "credential_referenced_by_workflow:true",
          "credential_target_system:source_control",
          "matched_target:built_in:deploy_workflow",
          "matched_target:built_in:kubernetes",
          "matched_target:built_in:release_automation",
          "permission:deploy.write",
          "permission:deployments.write",
          "permission:pull_request.write",
          "permission:repo.write",
          "repo_workflow_secret_correlation",
          "scope:source_control_write",
          "subject:cloud_admin_key",
          "target_system:source_control",
          "wch-2514b320edea",
          "wch-63302c190caa",
          "workflow_secret_refs",
          "write_path:deploy",
          "write_path:write_capable",
          "write_path_class:deploy_write",
          "write_path_class:pr_write",
          "write_path_class:production_adjacent_write",
          "write_path_class:release_write",
          "write_path_class:repo_write",
          "write_path_class:write"
        ],
        "reason_codes": [
          "precondition:effect_contract:missing",
          "precondition:effect_contract:unknown"
        ]
      },
      {
        "requirement_id": "pacp-b0f00ca426d2414a",
        "kind": "required_check",
        "required_constraint": "check:required",
        "acceptable_producers": [
          "ci",
          "control_declaration",
          "gait_policy"
        ],
        "max_age": "PT24H",
        "evidence_state": "unknown",
        "freshness_state": "unknown",
        "evidence_refs": [
          ".gait/policy.yaml",
          "approval_status=unapproved",
          "baseline:discovered_surface",
          "credential_likely_scope:source_control_write",
          "credential_present:true",
          "credential_referenced_by_workflow:true",
          "credential_target_system:source_control",
          "matched_target:built_in:deploy_workflow",
          "matched_target:built_in:kubernetes",
          "matched_target:built_in:release_automation",
          "permission:deploy.write",
          "permission:deployments.write",
          "permission:pull_request.write",
          "permission:repo.write",
          "repo_workflow_secret_correlation",
          "scope:source_control_write",
          "subject:cloud_admin_key",
          "target_system:source_control",
          "wch-2514b320edea",
          "wch-63302c190caa",
          "workflow_secret_refs",
          "write_path:deploy",
          "write_path:write_capable",
          "write_path_class:deploy_write",
          "write_path_class:pr_write",
          "write_path_class:production_adjacent_write",
          "write_path_class:release_write",
          "write_path_class:repo_write",
          "write_path_class:write"
        ],
        "reason_codes": [
          "precondition:required_check:missing",
          "precondition:required_check:unknown"
        ]
      },
      {
        "requirement_id": "pacp-e337bd0fa1fa3706",
        "kind": "forbidden_effect",
        "required_constraint": "effect:not_unbounded",
        "acceptable_producers": [
          "control_declaration",
          "gait_policy"
        ],
        "max_age": "PT24H",
        "evidence_state": "unknown",
        "freshness_state": "unknown",
        "evidence_refs": [
          ".gait/policy.yaml",
          "approval_status=unapproved",
          "baseline:discovered_surface",
          "credential_likely_scope:source_control_write",
          "credential_present:true",
          "credential_referenced_by_workflow:true",
          "credential_target_system:source_control",
          "matched_target:built_in:deploy_workflow",
          "matched_target:built_in:kubernetes",
          "matched_target:built_in:release_automation",
          "permission:deploy.write",
          "permission:deployments.write",
          "permission:pull_request.write",
          "permission:repo.write",
          "repo_workflow_secret_correlation",
          "scope:source_control_write",
          "subject:cloud_admin_key",
          "target_system:source_control",
          "wch-2514b320edea",
          "wch-63302c190caa",
          "workflow_secret_refs",
          "write_path:deploy",
          "write_path:write_capable",
          "write_path_class:deploy_write",
          "write_path_class:pr_write",
          "write_path_class:production_adjacent_write",
          "write_path_class:release_write",
          "write_path_class:repo_write",
          "write_path_class:write"
        ],
        "reason_codes": [
          "precondition:forbidden_effect:missing",
          "precondition:forbidden_effect:unknown"
        ]
      },
      {
        "requirement_id": "pacp-efb97cb3c669927d",
        "kind": "credential_mode",
        "required_constraint": "credential_mode:ephemeral",
        "observed_value": "ephemeral",
        "observed_result": "ephemeral",
        "acceptable_producers": [
          "credential_authority"
        ],
        "max_age": "PT24H",
        "evidence_state": "unknown",
        "freshness_state": "unknown",
        "evidence_refs": [
          ".gait/policy.yaml",
          "approval_status=unapproved",
          "baseline:discovered_surface",
          "credential_likely_scope:source_control_write",
          "credential_present:true",
          "credential_referenced_by_workflow:true",
          "credential_target_system:source_control",
          "matched_target:built_in:deploy_workflow",
          "matched_target:built_in:kubernetes",
          "matched_target:built_in:release_automation",
          "permission:deploy.write",
          "permission:deployments.write",
          "permission:pull_request.write",
          "permission:repo.write",
          "repo_workflow_secret_correlation",
          "scope:source_control_write",
          "subject:cloud_admin_key",
          "target_system:source_control",
          "wch-2514b320edea",
          "wch-63302c190caa",
          "workflow_secret_refs",
          "write_path:deploy",
          "write_path:write_capable",
          "write_path_class:deploy_write",
          "write_path_class:pr_write",
          "write_path_class:production_adjacent_write",
          "write_path_class:release_write",
          "write_path_class:repo_write",
          "write_path_class:write"
        ],
        "reason_codes": [
          "precondition:credential_mode:unknown"
        ]
      },
      {
        "requirement_id": "pacp-f835ded4dbd5439a",
        "kind": "expected_effect",
        "required_constraint": "effect:release_publish",
        "observed_value": "release_publish",
        "observed_result": "release_publish",
        "acceptable_producers": [
          "action_path"
        ],
        "max_age": "PT24H",
        "evidence_state": "unknown",
        "freshness_state": "unknown",
        "evidence_refs": [
          ".gait/policy.yaml",
          "approval_status=unapproved",
          "baseline:discovered_surface",
          "credential_likely_scope:source_control_write",
          "credential_present:true",
          "credential_referenced_by_workflow:true",
          "credential_target_system:source_control",
          "matched_target:built_in:deploy_workflow",
          "matched_target:built_in:kubernetes",
          "matched_target:built_in:release_automation",
          "permission:deploy.write",
          "permission:deployments.write",
          "permission:pull_request.write",
          "permission:repo.write",
          "repo_workflow_secret_correlation",
          "scope:source_control_write",
          "subject:cloud_admin_key",
          "target_system:source_control",
          "wch-2514b320edea",
          "wch-63302c190caa",
          "workflow_secret_refs",
          "write_path:deploy",
          "write_path:write_capable",
          "write_path_class:deploy_write",
          "write_path_class:pr_write",
          "write_path_class:production_adjacent_write",
          "write_path_class:release_write",
          "write_path_class:repo_write",
          "write_path_class:write"
        ],
        "reason_codes": [
          "precondition:expected_effect:unknown"
        ]
      }
    ],
    "confirmation_requirement": {
      "mode": "not_required",
      "required": false,
      "evidence_state": "verified",
      "freshness_state": "unknown",
      "evidence_refs": [
        ".gait/policy.yaml",
        "approval_status=unapproved",
        "baseline:discovered_surface",
        "credential_likely_scope:source_control_write",
        "credential_present:true",
        "credential_referenced_by_workflow:true",
        "credential_target_system:source_control",
        "matched_target:built_in:deploy_workflow",
        "matched_target:built_in:kubernetes",
        "matched_target:built_in:release_automation",
        "permission:deploy.write",
        "permission:deployments.write",
        "permission:pull_request.write",
        "permission:repo.write",
        "repo_workflow_secret_correlation",
        "scope:source_control_write",
        "subject:cloud_admin_key",
        "target_system:source_control",
        "wch-2514b320edea",
        "wch-63302c190caa",
        "workflow_secret_refs",
        "write_path:deploy",
        "write_path:write_capable",
        "write_path_class:deploy_write",
        "write_path_class:pr_write",
        "write_path_class:production_adjacent_write",
        "write_path_class:release_write",
        "write_path_class:repo_write",
        "write_path_class:write"
      ],
      "reason_codes": [
        "confirmation:not_required"
      ]
    },
    "approval_requirement": {
      "required": false,
      "approver_roles": [
        "control_owner",
        "security_reviewer"
      ],
      "minimum_approvals": 0,
      "separation_of_duties": [
        "requester_must_not_approve"
      ],
      "scope_digest": "sha256:80445c5964356f5dd9dfd4858a87ba34a1cf316187980c23bc79f8524c116c27",
      "validity_window": "PT24H",
      "reapproval_triggers": [
        "contract_content_change",
        "scope_digest_change"
      ],
      "evidence_state": "verified",
      "freshness_state": "unknown",
      "evidence_refs": [
        ".gait/policy.yaml",
        "approval_status=unapproved",
        "baseline:discovered_surface",
        "credential_likely_scope:source_control_write",
        "credential_present:true",
        "credential_referenced_by_workflow:true",
        "credential_target_system:source_control",
        "matched_target:built_in:deploy_workflow",
        "matched_target:built_in:kubernetes",
        "matched_target:built_in:release_automation",
        "permission:deploy.write",
        "permission:deployments.write",
        "permission:pull_request.write",
        "permission:repo.write",
        "repo_workflow_secret_correlation",
        "scope:source_control_write",
        "subject:cloud_admin_key",
        "target_system:source_control",
        "wch-2514b320edea",
        "wch-63302c190caa",
        "workflow_secret_refs",
        "write_path:deploy",
        "write_path:write_capable",
        "write_path_class:deploy_write",
        "write_path_class:pr_write",
        "write_path_class:production_adjacent_write",
        "write_path_class:release_write",
        "write_path_class:repo_write",
        "write_path_class:write"
      ],
      "reason_codes": [
        "approval:not_required"
      ]
    },
    "compensation_requirement": {
      "required": true,
      "kind": "documented_recovery",
      "target": "built_in:deploy_workflow+built_in:kubernetes+built_in:release_automation",
      "execution_window": "PT24H",
      "verification_required": true,
      "acceptable_producers": [
        "gait_policy",
        "control_declaration"
      ],
      "evidence_state": "unknown",
      "freshness_state": "unknown",
      "evidence_refs": [
        ".gait/policy.yaml",
        "approval_status=unapproved",
        "baseline:discovered_surface",
        "credential_likely_scope:source_control_write",
        "credential_present:true",
        "credential_referenced_by_workflow:true",
        "credential_target_system:source_control",
        "matched_target:built_in:deploy_workflow",
        "matched_target:built_in:kubernetes",
        "matched_target:built_in:release_automation",
        "permission:deploy.write",
        "permission:deployments.write",
        "permission:pull_request.write",
        "permission:repo.write",
        "repo_workflow_secret_correlation",
        "scope:source_control_write",
        "subject:cloud_admin_key",
        "target_system:source_control",
        "wch-2514b320edea",
        "wch-63302c190caa",
        "workflow_secret_refs",
        "write_path:deploy",
        "write_path:write_capable",
        "write_path_class:deploy_write",
        "write_path_class:pr_write",
        "write_path_class:production_adjacent_write",
        "write_path_class:release_write",
        "write_path_class:repo_write",
        "write_path_class:write"
      ],
      "reason_codes": [
        "compensation:required"
      ]
    },
    "lifecycle_observations": [
      {
        "observation_id": "pacl-044e8ea0487a3701",
        "kind": "proposal_creation",
        "producer": "wrkr",
        "evidence_state": "verified",
        "freshness_state": "fresh",
        "observed_at": "2026-07-19T00:00:00Z",
        "evidence_refs": [
          "interop:package-to-release"
        ],
        "proof_refs": [
          "proof:interop:package-to-release"
        ]
      }
    ]
  }
}
